igor2/__init__.py
igor2/_version.py
igor2/binarywave.py
igor2/packed.py
igor2/struct.py
igor2/util.py
igor2/cli/__init__.py
igor2/cli/igorbinarywave.py
igor2/cli/igorpackedexperiment.py
igor2/cli/script.py
igor2/record/__init__.py
igor2/record/base.py
igor2/record/folder.py
igor2/record/history.py
igor2/record/packedfile.py
igor2/record/procedure.py
igor2/record/variables.py
igor2/record/wave.py
igor2-0.5.12.dist-info/licenses/LICENSE
igor2-0.5.12.dist-info/METADATA
igor2-0.5.12.dist-info/WHEEL
igor2-0.5.12.dist-info/entry_points.txt
igor2-0.5.12.dist-info/top_level.txt
igor2-0.5.12.dist-info/RECORD
