Metadata-Version: 2.4
Name: igor2
Version: 0.5.12
Summary: interface for reading binary IGOR files
Author: Paul Kienzle, W. Trevor King, Aurelien Jaquier, Zbigniew Jędrzejewski-Szmek, Paul Müller
License: GNU Lesser General Public License v3 or later (LGPLv3+)
Project-URL: Issues, https://github.com/AFM-analysis/igor2/issues
Project-URL: Source, https://github.com/AFM-analysis/igor2
Classifier: Intended Audience :: Developers
Classifier: Intended Audience :: Science/Research
Classifier: Operating System :: OS Independent
Classifier: License :: OSI Approved :: GNU Lesser General Public License v3 or later (LGPLv3+)
Classifier: Programming Language :: Python :: 3
Requires-Python: <4,>=3.6
License-File: LICENSE
Requires-Dist: numpy>=1.19.2
Provides-Extra: cli
Requires-Dist: matplotlib; extra == "cli"
Provides-Extra: dev
Requires-Dist: pytest; extra == "dev"
Dynamic: license-file
